setup.py
PyStorAI/__init__.py
PyStorAI/storyboard.py
PyStorAI.egg-info/PKG-INFO
PyStorAI.egg-info/SOURCES.txt
PyStorAI.egg-info/dependency_links.txt
PyStorAI.egg-info/top_level.txt